ctfh/__init__.py
ctfh/main.py
ctfh/menu.py
ctfh/utils.py
ctfh/modules/__init__.py
ctfh/modules/binary.py
ctfh/modules/ciphers.py
ctfh/modules/encoding.py
ctfh/modules/fuzzing.py
ctfh/modules/hashing.py
ctfh/modules/javascript.py
ctfh/modules/steganography.py
ctfh/modules/vulnerability.py
ctfh-1.1.0.dist-info/METADATA
ctfh-1.1.0.dist-info/WHEEL
ctfh-1.1.0.dist-info/entry_points.txt
ctfh-1.1.0.dist-info/top_level.txt
ctfh-1.1.0.dist-info/RECORD
