Metadata-Version: 2.4
Name: ctfh
Version: 1.1.0
Summary: Interactive CTF, Cryptography & Cybersecurity Toolkit
Home-page: https://github.com/ghanishpatil08/ctfh.git
Author: Ghanish Patil
Classifier: Development Status :: 4 - Beta
Classifier: Intended Audience :: Education
Classifier: Topic :: Security
Classifier: Topic :: Education
Classifier: Programming Language :: Python :: 3
Classifier: Programming Language :: Python :: 3.10
Classifier: Programming Language :: Python :: 3.11
Classifier: Programming Language :: Python :: 3.12
Classifier: License :: OSI Approved :: MIT License
Classifier: Operating System :: OS Independent
Requires-Python: >=3.10
Requires-Dist: colorama>=0.4.6
Requires-Dist: requests>=2.31.0
Provides-Extra: full
Requires-Dist: Pillow>=10.0.0; extra == "full"
Requires-Dist: jsbeautifier>=1.14.0; extra == "full"
Requires-Dist: base58>=2.1.0; extra == "full"
Dynamic: author
Dynamic: classifier
Dynamic: description
Dynamic: description-content-type
Dynamic: home-page
Dynamic: provides-extra
Dynamic: requires-dist
Dynamic: requires-python
Dynamic: summary
